minydra/__init__.py
minydra/console.py
minydra/dict.py
minydra/exceptions.py
minydra/parser.py
minydra/utils.py
minydra-0.1.6.dist-info/LICENSE
minydra-0.1.6.dist-info/METADATA
minydra-0.1.6.dist-info/WHEEL
minydra-0.1.6.dist-info/top_level.txt
minydra-0.1.6.dist-info/RECORD
