Metadata-Version: 2.1
Name: minydra
Version: 0.1.6
Summary: Easily parse arbitrary arguments from the command line without dependencies
Home-page: https://github.com/vict0rsch/minydra
Author: Victor Schmidt
Author-email: not.an.address@yes.com
License: UNKNOWN
Platform: UNKNOWN
Classifier: Programming Language :: Python :: 3
Classifier: License :: OSI Approved :: MIT License
Classifier: Development Status :: 3 - Alpha
Classifier: Topic :: Utilities
Requires-Python: >=3.6
Provides-Extra: yaml
Requires-Dist: PyYaml ; extra == 'yaml'
